{
  "id": "deck_vitamin_c-s03",
  "layout": "two_columns_image",
  "section": "Витамин C",
  "title": "Синтез коллагена и фотозащита",
  "subtitle": "Влияние топической L-аскорбиновой кислоты на дермальный матрикс",
  "body": [
    {
      "type": "bullet",
      "text": "Активирует синтез коллагена I и III типов путем увеличения уровней мРНК in vivo."
    },
    {
      "type": "bullet",
      "text": "Защищает клетки кожи от индуцированного ультрафиолетом фотоповреждения."
    },
    {
      "type": "bullet",
      "text": "Стимулирует неоколлагенез и улучшает структурное состояние дермы."
    }
  ],
  "media": {
    "type": "image",
    "asset": "collagen_synthesis.svg",
    "fit": "cover",
    "caption": "Схема регуляции синтеза коллагена I и III типов под действием L-аскорбиновой кислоты"
  },
  "components": {},
  "disclaimers": [
    "Только для практикующих специалистов"
  ],
  "source_refs": [
    "fact_0021",
    "fact_0030",
    "fact_0046",
    "SRC-A023",
    "SRC-A029"
  ],
  "notes": "Клинические эффекты стимуляции коллагена и УФ-защиты"
}
